{
  "subjects": [
    {
      "id": "ug-his-o-level",
      "name": "History & Political Education",
      "country": "Uganda",
      "level": "O-Level",
      "classLevels": [
        "S1",
        "S2",
        "S3",
        "S4"
      ],
      "category": "Core",
      "active": true,
      "topics": [
        {
          "id": "ug-his-s1-1",
          "subjectId": "ug-his-o-level",
          "classLevel": "S1",
          "name": "Introduction to History & Political Education",
          "order": 1,
          "levelGroup": "Lower Secondary"
        },
        {
          "id": "ug-his-s1-2",
          "subjectId": "ug-his-o-level",
          "classLevel": "S1",
          "name": "Sources and Importance of History",
          "order": 2,
          "levelGroup": "Lower Secondary"
        },
        {
          "id": "ug-his-s1-3",
          "subjectId": "ug-his-o-level",
          "classLevel": "S1",
          "name": "East Africa and Eastern Africa",
          "order": 3,
          "levelGroup": "Lower Secondary"
        },
        {
          "id": "ug-his-s1-4",
          "subjectId": "ug-his-o-level",
          "classLevel": "S1",
          "name": "Early Societies",
          "order": 4,
          "levelGroup": "Lower Secondary"
        },
        {
          "id": "ug-his-s1-5",
          "subjectId": "ug-his-o-level",
          "classLevel": "S1",
          "name": "Migration and Settlement",
          "order": 5,
          "levelGroup": "Lower Secondary"
        },
        {
          "id": "ug-his-s1-6",
          "subjectId": "ug-his-o-level",
          "classLevel": "S1",
          "name": "Traditional Political Organization",
          "order": 6,
          "levelGroup": "Lower Secondary"
        },
        {
          "id": "ug-his-s1-7",
          "subjectId": "ug-his-o-level",
          "classLevel": "S1",
          "name": "Culture, Leadership, and Citizenship",
          "order": 7,
          "levelGroup": "Lower Secondary"
        },
        {
          "id": "ug-his-s2-1",
          "subjectId": "ug-his-o-level",
          "classLevel": "S2",
          "name": "External Contacts",
          "order": 1,
          "levelGroup": "Lower Secondary"
        },
        {
          "id": "ug-his-s2-2",
          "subjectId": "ug-his-o-level",
          "classLevel": "S2",
          "name": "Trade",
          "order": 2,
          "levelGroup": "Lower Secondary"
        },
        {
          "id": "ug-his-s2-3",
          "subjectId": "ug-his-o-level",
          "classLevel": "S2",
          "name": "Missionaries",
          "order": 3,
          "levelGroup": "Lower Secondary"
        },
        {
          "id": "ug-his-s2-4",
          "subjectId": "ug-his-o-level",
          "classLevel": "S2",
          "name": "Colonial Rule",
          "order": 4,
          "levelGroup": "Lower Secondary"
        },
        {
          "id": "ug-his-s2-5",
          "subjectId": "ug-his-o-level",
          "classLevel": "S2",
          "name": "Colonial Administration",
          "order": 5,
          "levelGroup": "Lower Secondary"
        },
        {
          "id": "ug-his-s2-6",
          "subjectId": "ug-his-o-level",
          "classLevel": "S2",
          "name": "African Resistance and Response",
          "order": 6,
          "levelGroup": "Lower Secondary"
        },
        {
          "id": "ug-his-s2-7",
          "subjectId": "ug-his-o-level",
          "classLevel": "S2",
          "name": "Social and Economic Change",
          "order": 7,
          "levelGroup": "Lower Secondary"
        },
        {
          "id": "ug-his-s3-1",
          "subjectId": "ug-his-o-level",
          "classLevel": "S3",
          "name": "Nationalism",
          "order": 1,
          "levelGroup": "Lower Secondary"
        },
        {
          "id": "ug-his-s3-2",
          "subjectId": "ug-his-o-level",
          "classLevel": "S3",
          "name": "Political Parties and Constitutional Change",
          "order": 2,
          "levelGroup": "Lower Secondary"
        },
        {
          "id": "ug-his-s3-3",
          "subjectId": "ug-his-o-level",
          "classLevel": "S3",
          "name": "Independence",
          "order": 3,
          "levelGroup": "Lower Secondary"
        },
        {
          "id": "ug-his-s3-4",
          "subjectId": "ug-his-o-level",
          "classLevel": "S3",
          "name": "Post-Independence Governance",
          "order": 4,
          "levelGroup": "Lower Secondary"
        },
        {
          "id": "ug-his-s3-5",
          "subjectId": "ug-his-o-level",
          "classLevel": "S3",
          "name": "Citizenship and Democracy",
          "order": 5,
          "levelGroup": "Lower Secondary"
        },
        {
          "id": "ug-his-s3-6",
          "subjectId": "ug-his-o-level",
          "classLevel": "S3",
          "name": "Regional Cooperation",
          "order": 6,
          "levelGroup": "Lower Secondary"
        },
        {
          "id": "ug-his-s4-1",
          "subjectId": "ug-his-o-level",
          "classLevel": "S4",
          "name": "Uganda Since Independence",
          "order": 1,
          "levelGroup": "Lower Secondary"
        },
        {
          "id": "ug-his-s4-2",
          "subjectId": "ug-his-o-level",
          "classLevel": "S4",
          "name": "East African Political Developments",
          "order": 2,
          "levelGroup": "Lower Secondary"
        },
        {
          "id": "ug-his-s4-3",
          "subjectId": "ug-his-o-level",
          "classLevel": "S4",
          "name": "Conflict and Peacebuilding",
          "order": 3,
          "levelGroup": "Lower Secondary"
        },
        {
          "id": "ug-his-s4-4",
          "subjectId": "ug-his-o-level",
          "classLevel": "S4",
          "name": "Regional Integration",
          "order": 4,
          "levelGroup": "Lower Secondary"
        },
        {
          "id": "ug-his-s4-5",
          "subjectId": "ug-his-o-level",
          "classLevel": "S4",
          "name": "Human Rights and Rule of Law",
          "order": 5,
          "levelGroup": "Lower Secondary"
        },
        {
          "id": "ug-his-s4-6",
          "subjectId": "ug-his-o-level",
          "classLevel": "S4",
          "name": "National Identity and Citizenship",
          "order": 6,
          "levelGroup": "Lower Secondary"
        }
      ]
    },
    {
      "id": "ug-his-a-level",
      "name": "History",
      "country": "Uganda",
      "level": "A-Level",
      "classLevels": [
        "S5",
        "S6"
      ],
      "category": "Principal",
      "active": true,
      "topics": [
        {
          "id": "ug-his-a1-1",
          "subjectId": "ug-his-a-level",
          "classLevel": "S5",
          "name": "East Africa and Uganda",
          "order": 1,
          "levelGroup": "Upper Secondary"
        },
        {
          "id": "ug-his-a1-2",
          "subjectId": "ug-his-a-level",
          "classLevel": "S5",
          "name": "Africa",
          "order": 2,
          "levelGroup": "Upper Secondary"
        },
        {
          "id": "ug-his-a1-3",
          "subjectId": "ug-his-a-level",
          "classLevel": "S6",
          "name": "World History and International Relations",
          "order": 3,
          "levelGroup": "Upper Secondary"
        }
      ]
    }
  ]
}