{
  "subjects": [
    {
      "id": "ug-bio-o-level",
      "name": "Biology",
      "country": "Uganda",
      "level": "O-Level",
      "classLevels": ["S1", "S2", "S3", "S4"],
      "category": "Core",
      "active": true,
      "topics": [
        {
          "id": "ug-bio-s1-1",
          "subjectId": "ug-bio-o-level",
          "classLevel": "S1",
          "name": "Introduction to Biology",
          "order": 1,
          "levelGroup": "Lower Secondary"
        },
        {
          "id": "ug-bio-s1-2",
          "subjectId": "ug-bio-o-level",
          "classLevel": "S1",
          "name": "Cells",
          "order": 2,
          "levelGroup": "Lower Secondary"
        },
        {
          "id": "ug-bio-s1-3",
          "subjectId": "ug-bio-o-level",
          "classLevel": "S1",
          "name": "Classification",
          "order": 3,
          "levelGroup": "Lower Secondary"
        },
        {
          "id": "ug-bio-s1-4",
          "subjectId": "ug-bio-o-level",
          "classLevel": "S1",
          "name": "Five Kingdoms",
          "order": 4,
          "levelGroup": "Lower Secondary"
        },
        {
          "id": "ug-bio-s1-5",
          "subjectId": "ug-bio-o-level",
          "classLevel": "S1",
          "name": "Viruses",
          "order": 5,
          "levelGroup": "Lower Secondary"
        },
        {
          "id": "ug-bio-s1-6",
          "subjectId": "ug-bio-o-level",
          "classLevel": "S1",
          "name": "Insects",
          "order": 6,
          "levelGroup": "Lower Secondary"
        },
        {
          "id": "ug-bio-s1-7",
          "subjectId": "ug-bio-o-level",
          "classLevel": "S1",
          "name": "Flowering Plants",
          "order": 7,
          "levelGroup": "Lower Secondary"
        },

        {
          "id": "ug-bio-s2-1",
          "subjectId": "ug-bio-o-level",
          "classLevel": "S2",
          "name": "Soil",
          "order": 1,
          "levelGroup": "Lower Secondary"
        },
        {
          "id": "ug-bio-s2-2",
          "subjectId": "ug-bio-o-level",
          "classLevel": "S2",
          "name": "Soil Erosion and Conservation",
          "order": 2,
          "levelGroup": "Lower Secondary"
        },
        {
          "id": "ug-bio-s2-3",
          "subjectId": "ug-bio-o-level",
          "classLevel": "S2",
          "name": "Plant and Animal Nutrition",
          "order": 3,
          "levelGroup": "Lower Secondary"
        },
        {
          "id": "ug-bio-s2-4",
          "subjectId": "ug-bio-o-level",
          "classLevel": "S2",
          "name": "Transport in Plants and Animals",
          "order": 4,
          "levelGroup": "Lower Secondary"
        },

        {
          "id": "ug-bio-s3-1",
          "subjectId": "ug-bio-o-level",
          "classLevel": "S3",
          "name": "Gaseous Exchange",
          "order": 1,
          "levelGroup": "Lower Secondary"
        },
        {
          "id": "ug-bio-s3-2",
          "subjectId": "ug-bio-o-level",
          "classLevel": "S3",
          "name": "Respiration",
          "order": 2,
          "levelGroup": "Lower Secondary"
        },
        {
          "id": "ug-bio-s3-3",
          "subjectId": "ug-bio-o-level",
          "classLevel": "S3",
          "name": "Excretion",
          "order": 3,
          "levelGroup": "Lower Secondary"
        },
        {
          "id": "ug-bio-s3-4",
          "subjectId": "ug-bio-o-level",
          "classLevel": "S3",
          "name": "Coordination",
          "order": 4,
          "levelGroup": "Lower Secondary"
        },
        {
          "id": "ug-bio-s3-5",
          "subjectId": "ug-bio-o-level",
          "classLevel": "S3",
          "name": "Receptor Organs",
          "order": 5,
          "levelGroup": "Lower Secondary"
        },
        {
          "id": "ug-bio-s3-6",
          "subjectId": "ug-bio-o-level",
          "classLevel": "S3",
          "name": "Locomotion",
          "order": 6,
          "levelGroup": "Lower Secondary"
        },
        {
          "id": "ug-bio-s3-7",
          "subjectId": "ug-bio-o-level",
          "classLevel": "S3",
          "name": "Growth and Development",
          "order": 7,
          "levelGroup": "Lower Secondary"
        },

        {
          "id": "ug-bio-s4-1",
          "subjectId": "ug-bio-o-level",
          "classLevel": "S4",
          "name": "Reproduction",
          "order": 1,
          "levelGroup": "Lower Secondary"
        },
        {
          "id": "ug-bio-s4-2",
          "subjectId": "ug-bio-o-level",
          "classLevel": "S4",
          "name": "Inheritance",
          "order": 2,
          "levelGroup": "Lower Secondary"
        },
        {
          "id": "ug-bio-s4-3",
          "subjectId": "ug-bio-o-level",
          "classLevel": "S4",
          "name": "Variation and Selection",
          "order": 3,
          "levelGroup": "Lower Secondary"
        },
        {
          "id": "ug-bio-s4-4",
          "subjectId": "ug-bio-o-level",
          "classLevel": "S4",
          "name": "Ecology",
          "order": 4,
          "levelGroup": "Lower Secondary"
        },
        {
          "id": "ug-bio-s4-5",
          "subjectId": "ug-bio-o-level",
          "classLevel": "S4",
          "name": "Food Chains and Food Webs",
          "order": 5,
          "levelGroup": "Lower Secondary"
        },
        {
          "id": "ug-bio-s4-6",
          "subjectId": "ug-bio-o-level",
          "classLevel": "S4",
          "name": "Biological Communities",
          "order": 6,
          "levelGroup": "Lower Secondary"
        },
        {
          "id": "ug-bio-s4-7",
          "subjectId": "ug-bio-o-level",
          "classLevel": "S4",
          "name": "Humans and the Environment",
          "order": 7,
          "levelGroup": "Lower Secondary"
        }
      ]
    },
    {
      "id": "ug-bio-a-level",
      "name": "Biology",
      "country": "Uganda",
      "level": "A-Level",
      "classLevels": ["S5", "S6"],
      "category": "Principal",
      "active": true,
      "topics": [
        {
          "id": "ug-bio-s5-1",
          "subjectId": "ug-bio-a-level",
          "classLevel": "S5",
          "name": "Cell Biology",
          "order": 1,
          "levelGroup": "Upper Secondary",
          "subtopics": [
            {"id": "ug-bio-s5-1-1", "topicId": "ug-bio-s5-1", "name": "Chemicals of Life", "order": 1},
            {"id": "ug-bio-s5-1-2", "topicId": "ug-bio-s5-1", "name": "Microscopy", "order": 2},
            {"id": "ug-bio-s5-1-3", "topicId": "ug-bio-s5-1", "name": "Ultrastructure of Plant, Animal, and Bacterial Cells", "order": 3},
            {"id": "ug-bio-s5-1-4", "topicId": "ug-bio-s5-1", "name": "Diversity of Tissues", "order": 4}
          ]
        },
        {
          "id": "ug-bio-s5-2",
          "subjectId": "ug-bio-a-level",
          "classLevel": "S5",
          "name": "Nutrition in Plants",
          "order": 2,
          "levelGroup": "Upper Secondary",
          "subtopics": [
            {"id": "ug-bio-s5-2-1", "topicId": "ug-bio-s5-2", "name": "Photosynthesis in C3 and C4 Plants", "order": 1}
          ]
        },
        {
          "id": "ug-bio-s5-3",
          "subjectId": "ug-bio-a-level",
          "classLevel": "S5",
          "name": "Transport in Humans",
          "order": 3,
          "levelGroup": "Upper Secondary",
          "subtopics": [
            {"id": "ug-bio-s5-3-1", "topicId": "ug-bio-s5-3", "name": "Transport of Gases in Humans", "order": 1},
            {"id": "ug-bio-s5-3-2", "topicId": "ug-bio-s5-3", "name": "Immunity in Humans", "order": 2}
          ]
        },
        {
          "id": "ug-bio-s5-4",
          "subjectId": "ug-bio-a-level",
          "classLevel": "S5",
          "name": "Respiration",
          "order": 4,
          "levelGroup": "Upper Secondary",
          "subtopics": [
            {"id": "ug-bio-s5-4-1", "topicId": "ug-bio-s5-4", "name": "Mitochondrion Structure and Function", "order": 1},
            {"id": "ug-bio-s5-4-2", "topicId": "ug-bio-s5-4", "name": "ATP Production Processes", "order": 2}
          ]
        },
        {
          "id": "ug-bio-s5-5",
          "subjectId": "ug-bio-a-level",
          "classLevel": "S5",
          "name": "Homeostasis",
          "order": 5,
          "levelGroup": "Upper Secondary",
          "subtopics": [
            {"id": "ug-bio-s5-5-1", "topicId": "ug-bio-s5-5", "name": "Negative Feedback Mechanisms", "order": 1},
            {"id": "ug-bio-s5-5-2", "topicId": "ug-bio-s5-5", "name": "Osmoregulation", "order": 2}
          ]
        },

        {
          "id": "ug-bio-s6-1",
          "subjectId": "ug-bio-a-level",
          "classLevel": "S6",
          "name": "Coordination",
          "order": 1,
          "levelGroup": "Upper Secondary",
          "subtopics": [
            {"id": "ug-bio-s6-1-1", "topicId": "ug-bio-s6-1", "name": "Plant Hormones and Responses", "order": 1},
            {"id": "ug-bio-s6-1-2", "topicId": "ug-bio-s6-1", "name": "Impulse Transmission", "order": 2},
            {"id": "ug-bio-s6-1-3", "topicId": "ug-bio-s6-1", "name": "Sensory Receptors", "order": 3},
            {"id": "ug-bio-s6-1-4", "topicId": "ug-bio-s6-1", "name": "Behaviour", "order": 4}
          ]
        },
        {
          "id": "ug-bio-s6-2",
          "subjectId": "ug-bio-a-level",
          "classLevel": "S6",
          "name": "Inheritance and Evolution",
          "order": 2,
          "levelGroup": "Upper Secondary",
          "subtopics": [
            {"id": "ug-bio-s6-2-1", "topicId": "ug-bio-s6-2", "name": "Nucleic Acids Structure and Function", "order": 1},
            {"id": "ug-bio-s6-2-2", "topicId": "ug-bio-s6-2", "name": "Gene Technology", "order": 2},
            {"id": "ug-bio-s6-2-3", "topicId": "ug-bio-s6-2", "name": "Mendelian and Non-Mendelian Inheritance", "order": 3},
            {"id": "ug-bio-s6-2-4", "topicId": "ug-bio-s6-2", "name": "Evolutionary Advancements in Life Process in Animals", "order": 4},
            {"id": "ug-bio-s6-2-5", "topicId": "ug-bio-s6-2", "name": "Speciation and Extinction", "order": 5}
          ]
        },
        {
          "id": "ug-bio-s6-3",
          "subjectId": "ug-bio-a-level",
          "classLevel": "S6",
          "name": "Growth in Plants and Development in Insects",
          "order": 3,
          "levelGroup": "Upper Secondary",
          "subtopics": [
            {"id": "ug-bio-s6-3-1", "topicId": "ug-bio-s6-3", "name": "Growth in Plants", "order": 1},
            {"id": "ug-bio-s6-3-2", "topicId": "ug-bio-s6-3", "name": "Metamorphosis in Insects", "order": 2}
          ]
        },
        {
          "id": "ug-bio-s6-4",
          "subjectId": "ug-bio-a-level",
          "classLevel": "S6",
          "name": "Ecology",
          "order": 4,
          "levelGroup": "Upper Secondary",
          "subtopics": [
            {"id": "ug-bio-s6-4-1", "topicId": "ug-bio-s6-4", "name": "Population Ecology", "order": 1},
            {"id": "ug-bio-s6-4-2", "topicId": "ug-bio-s6-4", "name": "Succession and Ecological Restoration", "order": 2},
            {"id": "ug-bio-s6-4-3", "topicId": "ug-bio-s6-4", "name": "Energy Flow in the Ecosystem", "order": 3},
            {"id": "ug-bio-s6-4-4", "topicId": "ug-bio-s6-4", "name": "Concept of Carbon Footprint", "order": 4},
            {"id": "ug-bio-s6-4-5", "topicId": "ug-bio-s6-4", "name": "Invasive Species", "order": 5},
            {"id": "ug-bio-s6-4-6", "topicId": "ug-bio-s6-4", "name": "Food Security", "order": 6}
          ]
        }
      ]
    }
  ]
}
